{
  "dhis2": {
    "system": "dhis2",
    "system_version": "stable-2-42-4",
    "concept_matches": [
      {
        "v2_concept": "Person",
        "external_entity": "TrackedEntityType(name=\"Person\")",
        "external_source": "extracted/tracked-entity-types.json",
        "match": "broad",
        "notes": "DHIS2 Person is not a fixed type: it is a TrackedEntityType whose attributes are configured per deployment. The demo instance ships eleven attributes (Unique ID, First name, Last name, Gender, Email, Date of birth, Address, City, National identifier, Mobile number, Civil status). This aligns semantically with v2 Person but DHIS2 treats the attribute set as open and deployment-specific. PersonName components are flat string fields on the DHIS2 side; v2 Person uses a structured `name` object.\n",
        "decomposition": [
          {
            "dhis2_field": "Unique ID",
            "target_concept": "Identifier",
            "target_property": "*",
            "notes": "Would become an Identifier record linked to the Person. DHIS2 stores it as a TrackedEntityAttribute with unique=true."
          },
          {
            "dhis2_field": "First name",
            "target_concept": "Person",
            "target_property": "name.given"
          },
          {
            "dhis2_field": "Last name",
            "target_concept": "Person",
            "target_property": "name.family"
          },
          {
            "dhis2_field": "Gender",
            "target_concept": "Person",
            "target_property": "gender",
            "notes": "Demo option set 'Gender' value-mapped via gender-type system_mappings."
          },
          {
            "dhis2_field": "Email",
            "target_concept": "Person",
            "target_property": "contact_points",
            "notes": "Would be decomposed into a ContactPoint with type=email. DHIS2 stores it flat."
          },
          {
            "dhis2_field": "Date of birth",
            "target_concept": "Person",
            "target_property": "date_of_birth"
          },
          {
            "dhis2_field": "Address",
            "target_concept": "Person",
            "target_property": "addresses",
            "notes": "DHIS2 holds a free-text address string; v2 Address is structured."
          },
          {
            "dhis2_field": "City",
            "target_concept": "Person",
            "target_property": "addresses",
            "notes": "Would be folded into an Address record with locality set."
          },
          {
            "dhis2_field": "National identifier",
            "target_concept": "Identifier",
            "target_property": "*",
            "notes": "Separate Identifier with identifier_type=national_id_number."
          },
          {
            "dhis2_field": "Mobile number",
            "target_concept": "Person",
            "target_property": "contact_points",
            "notes": "ContactPoint with type=mobile_phone."
          },
          {
            "dhis2_field": "Civil status",
            "target_concept": "Person",
            "target_property": "marital_status",
            "notes": "Demo option set value-mapped via marital-status system_mappings."
          }
        ]
      },
      {
        "v2_concept": "Organization",
        "external_entity": "OrganisationUnit",
        "external_source": "extracted/entities.json:OrganisationUnit",
        "match": "related",
        "notes": "OrganisationUnit is the single tree DHIS2 uses for anything place-shaped (countries, regions, districts, facilities, offices). It conflates what v2 separates into Organization, Location, GeographicArea, and HealthFacility. Mapping to Organization applies when an OrganisationUnit represents a service-delivery actor (a ministry, a facility's administrative owner) rather than a geographical or physical place.\n"
      },
      {
        "v2_concept": "Location",
        "external_entity": "OrganisationUnit",
        "external_source": "extracted/entities.json:OrganisationUnit",
        "match": "related",
        "notes": "When an OrganisationUnit carries `geometry` (point or polygon) or `featureType` it functions as a physical place. v2 Location covers that physical-place aspect; the same OrganisationUnit record may simultaneously be a v2 Organization and a v2 Location.\n"
      },
      {
        "v2_concept": "HealthFacility",
        "external_entity": "OrganisationUnit",
        "external_source": "extracted/entities.json:OrganisationUnit",
        "match": "related",
        "notes": "DHIS2 has no HealthFacility type. Facilities are leaf-ish nodes in the OrganisationUnit tree, typically distinguished by level or by an OrganisationUnitGroup tagging. Deployments often define a \"Facility type\" option set configured per country.\n",
        "decomposition": [
          {
            "dhis2_field": "level",
            "target_concept": "HealthFacility",
            "target_property": null,
            "notes": "Tree level is how deployments distinguish facility nodes from district/region nodes."
          },
          {
            "dhis2_field": "organisationUnitGroups",
            "target_concept": "HealthFacility",
            "target_property": "facility_type",
            "notes": "OU groups commonly carry 'Hospital', 'Health centre', 'Clinic' classifications; these would map via the health-facility-type vocabulary."
          },
          {
            "dhis2_field": "geometry",
            "target_concept": "Location",
            "target_property": "geometry"
          },
          {
            "dhis2_field": "featureType",
            "target_concept": "Location",
            "target_property": "geometry",
            "notes": "NONE/POINT/POLYGON/MULTI_POLYGON/SYMBOL; shapes the geometry representation."
          }
        ]
      },
      {
        "v2_concept": "GeographicArea",
        "external_entity": "OrganisationUnit",
        "external_source": "extracted/entities.json:OrganisationUnit",
        "match": "related",
        "notes": "Upper levels of the OrganisationUnit tree (country, region, district) function as geographic areas. The same conflation note applies: v2 GeographicArea is one projection of an OrganisationUnit, not a dedicated DHIS2 type.\n"
      },
      {
        "v2_concept": "Event",
        "external_entity": "TrackerEvent",
        "external_source": "extracted/entities.json:TrackerEvent",
        "match": "related",
        "notes": "v2 Event is an abstract supertype for real-world occurrences with temporal grounding (vital events, payment events, hazard events). DHIS2 TrackerEvent is a data-collection occurrence: when a form was filled in, by whom, at which OrganisationUnit. The semantic overlap is partial: a TrackerEvent can represent a vaccination administration (real-world event) or a household survey completion (collection event). Deployments need to inspect the ProgramStage to know which.\n",
        "decomposition": [
          {
            "dhis2_field": "occurredAt",
            "target_concept": "Event",
            "target_property": "event_date"
          },
          {
            "dhis2_field": "scheduledAt",
            "target_concept": "Event",
            "target_property": null,
            "notes": "Scheduling metadata; not a v2 Event property."
          },
          {
            "dhis2_field": "orgUnit",
            "target_concept": "Event",
            "target_property": "event_location"
          },
          {
            "dhis2_field": "dataValues",
            "target_concept": "Profile",
            "target_property": "observations",
            "notes": "Observation data collected at this event. Maps to a v2 Profile whose subtype depends on the ProgramStage semantics."
          },
          {
            "dhis2_field": "enrollment",
            "target_concept": "Event",
            "target_property": null,
            "notes": "Backlink to TrackerEnrollment; not a v2 Event field. Surfaces in the sp/Enrollment decomposition instead."
          },
          {
            "dhis2_field": "status",
            "target_concept": "Event",
            "target_property": null,
            "notes": "EventStatus (ACTIVE, COMPLETED, VISITED, SCHEDULE, OVERDUE, SKIPPED) is a workflow state, not an event property."
          }
        ]
      },
      {
        "v2_concept": "Relationship",
        "external_entity": "TrackerRelationship",
        "external_source": "extracted/entities.json:TrackerRelationship",
        "match": "broad",
        "notes": "TrackerRelationship links any two tracker items (TrackedEntity, Enrollment, or Event). v2 Relationship is narrower: it links parties only. The type and direction metadata live in RelationshipType, not on the Relationship itself.\n",
        "decomposition": [
          {
            "dhis2_field": "from",
            "target_concept": "Relationship",
            "target_property": "party_a",
            "notes": "TrackerRelationshipItem resolves to one of TrackedEntity/Enrollment/Event. Only the TrackedEntity case maps cleanly to v2 party slots."
          },
          {
            "dhis2_field": "to",
            "target_concept": "Relationship",
            "target_property": "party_b"
          },
          {
            "dhis2_field": "relationshipType",
            "target_concept": "Relationship",
            "target_property": "relationship_type",
            "notes": "Country-configured; no fixed enum. RelationshipType additionally carries bidirectionality via fromConstraint/toConstraint."
          },
          {
            "dhis2_field": "bidirectional",
            "target_concept": "Relationship",
            "target_property": null,
            "notes": "Property of the RelationshipType, not the Relationship record in v2."
          }
        ]
      },
      {
        "v2_concept": "Identifier",
        "external_entity": "TrackedEntityAttribute",
        "external_source": "extracted/entities.json:TrackedEntityAttribute",
        "match": "narrow",
        "notes": "DHIS2 TrackedEntityAttributes with `unique=true` and (typically) `valueType=TEXT` function as identifiers. The demo instance uses \"Unique ID\" and \"National identifier\" this way. v2 Identifier is a first-class entity with type, issuer, validity; DHIS2 collapses all of that into a TEA configuration plus the stored attribute value.\n"
      },
      {
        "v2_concept": "Profile",
        "external_entity": "ProgramStage",
        "external_source": "extracted/entities.json:ProgramStage",
        "match": "related",
        "notes": "v2 Profile is an abstract supertype for observation records (FunctioningProfile, SocioEconomicProfile, etc.). DHIS2 expresses the same intent structurally: a ProgramStage defines which data elements are collected; a TrackerEvent is an instance; each TrackerDataValue on that event is one observation. Reading a v2 Profile from DHIS2 means projecting an event's DataValues into the Profile shape. The mapping is a pattern, not a type equivalence.\n"
      },
      {
        "v2_concept": "sp/Enrollment",
        "external_entity": "TrackerEnrollment",
        "external_source": "extracted/entities.json:TrackerEnrollment",
        "match": "broad",
        "notes": "TrackerEnrollment is DHIS2's operational record of a TrackedEntity joining a Program. It is broader than sp/Enrollment: it applies to any tracker program, health or otherwise. The eligibility/entitlement side of sp/Enrollment has no DHIS2 counterpart; a TrackerEnrollment has been admitted by the time it exists.\n",
        "decomposition": [
          {
            "dhis2_field": "trackedEntity",
            "target_concept": "sp/Enrollment",
            "target_property": "participant"
          },
          {
            "dhis2_field": "program",
            "target_concept": "sp/Enrollment",
            "target_property": "program"
          },
          {
            "dhis2_field": "enrolledAt",
            "target_concept": "sp/Enrollment",
            "target_property": "start_date"
          },
          {
            "dhis2_field": "occurredAt",
            "target_concept": "sp/Enrollment",
            "target_property": null,
            "notes": "Date of an incident event captured on enrollment (e.g., date of diagnosis). No direct v2 slot; often a domain-specific field."
          },
          {
            "dhis2_field": "completedAt",
            "target_concept": "sp/Enrollment",
            "target_property": "end_date"
          },
          {
            "dhis2_field": "status",
            "target_concept": "sp/Enrollment",
            "target_property": "status",
            "notes": "EnrollmentStatus (ACTIVE, COMPLETED, CANCELLED) value-mapped via sp/enrollment-status system_mappings."
          },
          {
            "dhis2_field": "orgUnit",
            "target_concept": "sp/Enrollment",
            "target_property": null,
            "notes": "OwningOU. In v2 this sits on Program or the enrolling office, not on Enrollment itself."
          },
          {
            "dhis2_field": "events",
            "target_concept": "sp/Enrollment",
            "target_property": null,
            "notes": "Child events within this enrollment. In v2 each would be a separate Event or Profile record referencing the Enrollment."
          },
          {
            "dhis2_field": "notes",
            "target_concept": "sp/Enrollment",
            "target_property": null,
            "notes": "Free-form caseworker notes. No v2 equivalent field."
          }
        ]
      },
      {
        "v2_concept": "sp/Program",
        "external_entity": "Program",
        "external_source": "extracted/entities.json:Program",
        "match": "broad",
        "notes": "DHIS2 Program is broader than sp/Program: it covers any tracker or event programme, including health surveillance and data collection forms. The benefit-schedule / entitlement side of sp/Program has no counterpart.\n",
        "decomposition": [
          {
            "dhis2_field": "name",
            "target_concept": "sp/Program",
            "target_property": "name"
          },
          {
            "dhis2_field": "description",
            "target_concept": "sp/Program",
            "target_property": "description"
          },
          {
            "dhis2_field": "programType",
            "target_concept": "sp/Program",
            "target_property": null,
            "notes": "WITH_REGISTRATION vs WITHOUT_REGISTRATION is DHIS2 architecture, not a v2 property."
          },
          {
            "dhis2_field": "trackedEntityType",
            "target_concept": "sp/Program",
            "target_property": "eligible_party_type",
            "notes": "Approximate: restricts which kind of Party can enrol."
          },
          {
            "dhis2_field": "programStages",
            "target_concept": "sp/Program",
            "target_property": null,
            "notes": "Workflow steps; not directly modeled in sp/Program. Would surface through linked Profile or Event configurations."
          },
          {
            "dhis2_field": "programTrackedEntityAttributes",
            "target_concept": "sp/Program",
            "target_property": null,
            "notes": "Attributes to collect on enrollment. In v2 these drive Profile/Identifier records rather than living on Program."
          },
          {
            "dhis2_field": "accessLevel",
            "target_concept": "sp/Program",
            "target_property": null,
            "notes": "OPEN/AUDITED/PROTECTED/CLOSED — confidentiality policy. No v2 equivalent."
          },
          {
            "dhis2_field": "organisationUnits",
            "target_concept": "sp/Program",
            "target_property": null,
            "notes": "Which OUs this program is rolled out to. v2 handles coverage through a different construct."
          }
        ]
      }
    ],
    "no_match": [
      {
        "v2_concept": "Agent",
        "reason": "Abstract supertype for Person/Organization/SoftwareAgent. DHIS2 has no analogous abstraction; User, TrackedEntity, and OrganisationUnit are unrelated types.\n"
      },
      {
        "v2_concept": "Party",
        "reason": "Abstract supertype for Person/Group. DHIS2 does not abstract \"beneficiary-side\" actors; TrackedEntity (the closest construct) is concrete and has no sibling for Group.\n"
      },
      {
        "v2_concept": "Address",
        "reason": "DHIS2 stores address as a free-text string TEA on Person. There is no structured Address type in the meta-model.\n"
      },
      {
        "v2_concept": "BiometricSample",
        "reason": "DHIS2 core does not model biometric enrolment. Attachments on a tracked entity via file resource TEAs are possible but carry no modality, template, or capture metadata.\n"
      },
      {
        "v2_concept": "ConsentRecord",
        "reason": "No consent-record construct in DHIS2. Programs can be configured with a `captureCoordinates` or `selectIncidentDatesInFuture` flag, but consent as a reified record is not modelled.\n"
      },
      {
        "v2_concept": "DeliveryItem",
        "reason": "DHIS2 is not a benefit-delivery system; no delivery-item concept."
      },
      {
        "v2_concept": "Family",
        "reason": "DHIS2 tracker has no first-class Family construct. Some deployments model kinship via Relationships between tracked entities; no reified Family group exists.\n"
      },
      {
        "v2_concept": "Farm",
        "reason": "DHIS2 does not model agricultural holdings."
      },
      {
        "v2_concept": "Group",
        "reason": "Abstract supertype for Family/Household/Farm. DHIS2 has no equivalent abstraction over collective parties.\n"
      },
      {
        "v2_concept": "GroupMembership",
        "reason": "No group-membership construct. The closest pattern is a TrackerRelationship with a parent/child-of-household RelationshipType, which does not carry role or validity.\n"
      },
      {
        "v2_concept": "HazardEvent",
        "reason": "DHIS2 does not model hazard events as a first-class type."
      },
      {
        "v2_concept": "Household",
        "reason": "No household construct in DHIS2 core (see Group above)."
      },
      {
        "v2_concept": "IdentityDocument",
        "reason": "DHIS2 records identifier values on a Person via unique TEAs, but does not reify the issuing document, its validity period, or jurisdiction.\n"
      },
      {
        "v2_concept": "InKindDelivery",
        "reason": "DHIS2 is not a benefit-delivery system."
      },
      {
        "v2_concept": "Instrument",
        "reason": "DHIS2 does not catalog data-collection instruments as reified records with authorship, version, and provenance. A ProgramStage plus its DataElements is the closest operational analogue but carries no Instrument metadata.\n"
      },
      {
        "v2_concept": "PaymentEvent",
        "reason": "DHIS2 is not a payment system."
      },
      {
        "v2_concept": "PrivacyNotice",
        "reason": "No privacy-notice construct in DHIS2 core."
      },
      {
        "v2_concept": "RegistrationOffice",
        "reason": "No registration-office construct. OrganisationUnits can represent offices but carry no distinct registration-office typing.\n"
      },
      {
        "v2_concept": "School",
        "reason": "DHIS2 does not model schools as a typed OrganisationUnit subtype."
      },
      {
        "v2_concept": "ScoringEvent",
        "reason": "DHIS2 has no construct recording the application of a scoring rule to observation data. Indicators exist in the aggregate analytics side but are out of scope for the meta-model mapping.\n"
      },
      {
        "v2_concept": "ScoringRule",
        "reason": "DHIS2 programIndicators and predictors can compute values, but they live in the analytics layer rather than in tracker metadata. They are out of scope here.\n"
      },
      {
        "v2_concept": "ServicePoint",
        "reason": "No generic service-point construct distinct from OrganisationUnit."
      },
      {
        "v2_concept": "SocioEconomicProfile",
        "reason": "Profile subtypes are not reified as types in DHIS2. A deployment could encode a socio-economic assessment as a ProgramStage but the meta-model does not name it.\n"
      },
      {
        "v2_concept": "FunctioningProfile",
        "reason": "Same pattern as SocioEconomicProfile: no Profile-subtype reification in the meta-model.\n"
      },
      {
        "v2_concept": "SoftwareAgent",
        "reason": "DHIS2 has a User model and API tokens, but no SoftwareAgent concept for recording the identity/version of scoring software or other automated actors.\n"
      },
      {
        "v2_concept": "Voucher",
        "reason": "DHIS2 is not a voucher-delivery system."
      },
      {
        "v2_concept": "VoucherRedemption",
        "reason": "Same as Voucher."
      },
      {
        "v2_concept": "WaterPoint",
        "reason": "No water-point construct; would be an OrganisationUnit subtype if modelled."
      },
      {
        "v2_concept": "sp/BenefitSchedule",
        "reason": "DHIS2 does not model benefit schedules."
      },
      {
        "v2_concept": "sp/EligibilityDecision",
        "reason": "DHIS2 has no eligibility-decision record. Admission is implicit in the existence of a TrackerEnrollment."
      },
      {
        "v2_concept": "sp/Entitlement",
        "reason": "DHIS2 is not an entitlement-management system."
      },
      {
        "v2_concept": "sp/Grievance",
        "reason": "No grievance/complaint workflow in DHIS2 core."
      },
      {
        "v2_concept": "sp/Referral",
        "reason": "DHIS2 can model referrals as tracker relationships or program events but has no first-class Referral type with status, origin, and destination facility semantics.\n"
      },
      {
        "v2_concept": "crvs/VitalEvent",
        "reason": "DHIS2 is not a CRVS. Births/deaths can be recorded as tracker events within a health programme, but not as legal vital events."
      },
      {
        "v2_concept": "crvs/Birth",
        "reason": "Not modelled in DHIS2. Birth Notification programs exist as deployment content; the meta-model does not name them."
      },
      {
        "v2_concept": "crvs/Death",
        "reason": "Not modelled in DHIS2. Mortality surveillance deployments exist; the meta-model does not name them."
      },
      {
        "v2_concept": "crvs/FetalDeath",
        "reason": "Not modelled in DHIS2."
      },
      {
        "v2_concept": "crvs/Marriage",
        "reason": "Not modelled in DHIS2."
      },
      {
        "v2_concept": "crvs/MarriageTermination",
        "reason": "Not modelled in DHIS2."
      },
      {
        "v2_concept": "crvs/Adoption",
        "reason": "Not modelled in DHIS2."
      },
      {
        "v2_concept": "crvs/Legitimation",
        "reason": "Not modelled in DHIS2."
      },
      {
        "v2_concept": "crvs/PaternityRecognition",
        "reason": "Not modelled in DHIS2."
      },
      {
        "v2_concept": "crvs/Parent",
        "reason": "No parent link type. Kinship can be expressed via tracker relationships but carries no parental-role semantics."
      },
      {
        "v2_concept": "crvs/Certificate",
        "reason": "No civil-status certificate record in DHIS2."
      },
      {
        "v2_concept": "crvs/CivilStatusDocument",
        "reason": "Abstract CRVS document supertype. DHIS2 does not model any civil-status documents."
      },
      {
        "v2_concept": "crvs/CivilStatusRecord",
        "reason": "No reified civil-status-record type in DHIS2."
      },
      {
        "v2_concept": "crvs/CivilStatusAnnotation",
        "reason": "No annotation construct for civil status updates."
      },
      {
        "v2_concept": "crvs/FamilyRegister",
        "reason": "DHIS2 does not model family registers (livret de famille, koseki, hukou)."
      },
      {
        "v2_concept": "crvs/Person",
        "reason": "Separate from universal Person, crvs/Person is the CRVS projection with civil-status-specific fields. DHIS2 has no CRVS layer, so the universal Person match already covers what DHIS2 represents.\n"
      },
      {
        "v2_vocabulary": "sex",
        "reason": "DHIS2 uses a single 'Gender' option set per deployment; no separate biological-sex vocabulary."
      },
      {
        "v2_vocabulary": "identifier-type",
        "reason": "Identifier types are per-TEA configuration, not a shared vocabulary."
      },
      {
        "v2_vocabulary": "document-type",
        "reason": "No identity-document model; no document-type vocabulary."
      },
      {
        "v2_vocabulary": "document-status",
        "reason": "No document model; no status vocabulary."
      },
      {
        "v2_vocabulary": "biometric-modality",
        "reason": "DHIS2 does not model biometrics."
      },
      {
        "v2_vocabulary": "biometric-subtype",
        "reason": "No biometrics in DHIS2."
      },
      {
        "v2_vocabulary": "biometric-exception-reason",
        "reason": "No biometrics in DHIS2."
      },
      {
        "v2_vocabulary": "impression-type",
        "reason": "No biometrics in DHIS2."
      },
      {
        "v2_vocabulary": "relationship-type",
        "reason": "DHIS2 RelationshipType is country-configured, not a fixed vocabulary."
      },
      {
        "v2_vocabulary": "group-type",
        "reason": "No Group supertype; no group-type vocabulary."
      },
      {
        "v2_vocabulary": "group-role",
        "reason": "No group-membership model; no role vocabulary."
      },
      {
        "v2_vocabulary": "country",
        "reason": "Countries are OrganisationUnits at the top level; DHIS2 has no ISO 3166 enum."
      },
      {
        "v2_vocabulary": "region",
        "reason": "UN M49 regions are not part of the DHIS2 meta-model."
      },
      {
        "v2_vocabulary": "language",
        "reason": "DHIS2 supports UI translations but has no ISO 639 vocabulary as such."
      },
      {
        "v2_vocabulary": "script",
        "reason": "No ISO 15924 script vocabulary in DHIS2."
      },
      {
        "v2_vocabulary": "currency",
        "reason": "No currency handling in DHIS2 core."
      },
      {
        "v2_vocabulary": "unit-of-measure",
        "reason": "Units are free-text on DataElement.valueType formatting; no shared UoM vocabulary."
      },
      {
        "v2_vocabulary": "education-level",
        "reason": "Per-deployment option set, not a core enum."
      },
      {
        "v2_vocabulary": "literacy",
        "reason": "Per-deployment option set."
      },
      {
        "v2_vocabulary": "school-level",
        "reason": "No school construct; no vocabulary."
      },
      {
        "v2_vocabulary": "school-type",
        "reason": "No school construct."
      },
      {
        "v2_vocabulary": "occupation",
        "reason": "Per-deployment option set; no ISCO alignment in core."
      },
      {
        "v2_vocabulary": "employment-status",
        "reason": "Per-deployment option set."
      },
      {
        "v2_vocabulary": "status-in-employment",
        "reason": "Per-deployment option set."
      },
      {
        "v2_vocabulary": "income-source",
        "reason": "Per-deployment option set."
      },
      {
        "v2_vocabulary": "health-facility-type",
        "reason": "OrganisationUnit classifications are per-deployment via OU groups."
      },
      {
        "v2_vocabulary": "health-facility-level",
        "reason": "Per-deployment."
      },
      {
        "v2_vocabulary": "facility-operational-status",
        "reason": "Per-deployment option set."
      },
      {
        "v2_vocabulary": "care-provider-type",
        "reason": "No shared vocabulary in DHIS2 core."
      },
      {
        "v2_vocabulary": "maternity-care-provider",
        "reason": "Per-deployment option set."
      },
      {
        "v2_vocabulary": "organization-type",
        "reason": "OrganisationUnitGroups serve this role but carry no fixed type vocabulary."
      },
      {
        "v2_vocabulary": "service-point-type",
        "reason": "No service-point concept."
      },
      {
        "v2_vocabulary": "registration-office-type",
        "reason": "No registration-office concept."
      },
      {
        "v2_vocabulary": "dwelling-type",
        "reason": "Per-deployment option set."
      },
      {
        "v2_vocabulary": "roof-material",
        "reason": "Per-deployment option set."
      },
      {
        "v2_vocabulary": "wall-material",
        "reason": "Per-deployment option set."
      },
      {
        "v2_vocabulary": "floor-material",
        "reason": "Per-deployment option set."
      },
      {
        "v2_vocabulary": "cooking-fuel",
        "reason": "Per-deployment option set."
      },
      {
        "v2_vocabulary": "sanitation-facility",
        "reason": "Per-deployment option set."
      },
      {
        "v2_vocabulary": "sanitation-service-level",
        "reason": "Per-deployment option set."
      },
      {
        "v2_vocabulary": "water-source",
        "reason": "Per-deployment option set."
      },
      {
        "v2_vocabulary": "water-point-type",
        "reason": "No water-point concept."
      },
      {
        "v2_vocabulary": "water-service-level",
        "reason": "Per-deployment option set."
      },
      {
        "v2_vocabulary": "settlement-type",
        "reason": "Per-deployment option set."
      },
      {
        "v2_vocabulary": "shelter-situation-type",
        "reason": "Per-deployment; typically humanitarian context."
      },
      {
        "v2_vocabulary": "land-tenure",
        "reason": "Per-deployment option set."
      },
      {
        "v2_vocabulary": "occupancy-arrangement",
        "reason": "Per-deployment option set."
      },
      {
        "v2_vocabulary": "household-asset",
        "reason": "Per-deployment option set."
      },
      {
        "v2_vocabulary": "ict-access",
        "reason": "Per-deployment option set."
      },
      {
        "v2_vocabulary": "livestock-type",
        "reason": "No livestock/agriculture model."
      },
      {
        "v2_vocabulary": "consent-status",
        "reason": "No consent-record model."
      },
      {
        "v2_vocabulary": "consent-record-type",
        "reason": "No consent-record model."
      },
      {
        "v2_vocabulary": "consent-expression",
        "reason": "No consent-record model."
      },
      {
        "v2_vocabulary": "legal-basis",
        "reason": "No consent-record model."
      },
      {
        "v2_vocabulary": "delegation-type",
        "reason": "No delegation model."
      },
      {
        "v2_vocabulary": "special-category-basis",
        "reason": "No consent-record model."
      },
      {
        "v2_vocabulary": "crvs/adoption-type",
        "reason": "DHIS2 is not a CRVS."
      },
      {
        "v2_vocabulary": "crvs/annotation-type",
        "reason": "DHIS2 is not a CRVS."
      },
      {
        "v2_vocabulary": "crvs/birth-attendant",
        "reason": "DHIS2 is not a CRVS. (Deployments can configure this via option sets in health programmes.)"
      },
      {
        "v2_vocabulary": "crvs/birth-type",
        "reason": "Same."
      },
      {
        "v2_vocabulary": "crvs/cause-of-death-method",
        "reason": "Same."
      },
      {
        "v2_vocabulary": "crvs/certificate-document-type",
        "reason": "No certificate model."
      },
      {
        "v2_vocabulary": "crvs/certificate-format",
        "reason": "No certificate model."
      },
      {
        "v2_vocabulary": "crvs/civil-status-record-type",
        "reason": "No civil-status-record model."
      },
      {
        "v2_vocabulary": "crvs/family-register-status",
        "reason": "No family-register model."
      },
      {
        "v2_vocabulary": "crvs/manner-of-death",
        "reason": "DHIS2 is not a CRVS."
      },
      {
        "v2_vocabulary": "crvs/marriage-termination-type",
        "reason": "DHIS2 is not a CRVS."
      },
      {
        "v2_vocabulary": "crvs/marriage-type",
        "reason": "DHIS2 is not a CRVS."
      },
      {
        "v2_vocabulary": "crvs/parent-establishment-basis",
        "reason": "DHIS2 is not a CRVS."
      },
      {
        "v2_vocabulary": "crvs/parental-role",
        "reason": "No Parent link type."
      },
      {
        "v2_vocabulary": "crvs/place-type",
        "reason": "DHIS2 is not a CRVS."
      },
      {
        "v2_vocabulary": "crvs/registration-status",
        "reason": "DHIS2 is not a CRVS."
      },
      {
        "v2_vocabulary": "crvs/registration-type",
        "reason": "DHIS2 is not a CRVS."
      },
      {
        "v2_vocabulary": "sp/benefit-frequency",
        "reason": "DHIS2 is not a benefit-delivery system."
      },
      {
        "v2_vocabulary": "sp/benefit-modality",
        "reason": "Same."
      },
      {
        "v2_vocabulary": "sp/conditionality-type",
        "reason": "No conditionality construct."
      },
      {
        "v2_vocabulary": "sp/eligibility-status",
        "reason": "No eligibility-decision model."
      },
      {
        "v2_vocabulary": "sp/enrollment-exit-reason",
        "reason": "No exit-reason vocabulary in core; DHIS2 EnrollmentStatus collapses COMPLETED/CANCELLED."
      },
      {
        "v2_vocabulary": "sp/entitlement-status",
        "reason": "No entitlement model."
      },
      {
        "v2_vocabulary": "sp/grievance-status",
        "reason": "No grievance model."
      },
      {
        "v2_vocabulary": "sp/grievance-type",
        "reason": "No grievance model."
      },
      {
        "v2_vocabulary": "sp/referral-status",
        "reason": "No Referral model."
      },
      {
        "v2_vocabulary": "sp/targeting-approach",
        "reason": "No targeting-approach vocabulary."
      },
      {
        "v2_vocabulary": "payment-status",
        "reason": "DHIS2 is not a payment system."
      },
      {
        "v2_vocabulary": "delivery-channel",
        "reason": "DHIS2 is not a delivery system."
      },
      {
        "v2_vocabulary": "withdrawal-channel",
        "reason": "DHIS2 is not a payment/delivery system."
      },
      {
        "v2_vocabulary": "administration-mode",
        "reason": "No administration-mode concept in DHIS2 core."
      },
      {
        "v2_vocabulary": "voucher-format",
        "reason": "No voucher model."
      },
      {
        "v2_vocabulary": "voucher-status",
        "reason": "No voucher model."
      },
      {
        "v2_vocabulary": "recipient-role",
        "reason": "No delivery model."
      },
      {
        "v2_vocabulary": "hazard-type",
        "reason": "No hazard-event model."
      },
      {
        "v2_vocabulary": "event-severity",
        "reason": "Per-deployment."
      },
      {
        "v2_vocabulary": "event-certainty",
        "reason": "Per-deployment."
      },
      {
        "v2_vocabulary": "displacement-status",
        "reason": "Per-deployment."
      },
      {
        "v2_vocabulary": "acute-malnutrition-severity",
        "reason": "Per-deployment; would be configured on a nutrition ProgramStage."
      },
      {
        "v2_vocabulary": "food-security-level",
        "reason": "Per-deployment."
      },
      {
        "v2_vocabulary": "wg-ss-domain",
        "reason": "The WG Short Set is deployed as a ProgramStage with specific DataElements and option sets in country configurations; not a core DHIS2 vocabulary."
      },
      {
        "v2_vocabulary": "functional-difficulty-severity",
        "reason": "Per-deployment; typically the WG-SS Likert scale."
      },
      {
        "v2_vocabulary": "functional-intensity",
        "reason": "Per-deployment."
      },
      {
        "v2_vocabulary": "aid-use-frequency",
        "reason": "Per-deployment."
      },
      {
        "v2_vocabulary": "mobility-aid-type",
        "reason": "Per-deployment."
      },
      {
        "v2_vocabulary": "daily-duration",
        "reason": "Per-deployment."
      },
      {
        "v2_vocabulary": "cfm-symptom-frequency",
        "reason": "Per-deployment (Child Functioning Module)."
      },
      {
        "v2_vocabulary": "cognition-remembering-extent",
        "reason": "Per-deployment."
      },
      {
        "v2_vocabulary": "cognition-remembering-frequency",
        "reason": "Per-deployment."
      },
      {
        "v2_vocabulary": "cognition-subdomain",
        "reason": "Per-deployment."
      },
      {
        "v2_vocabulary": "comparative-behaviour-scale",
        "reason": "Per-deployment."
      },
      {
        "v2_vocabulary": "symptom-chronicity",
        "reason": "Per-deployment."
      },
      {
        "v2_vocabulary": "symptom-period-frequency",
        "reason": "Per-deployment."
      },
      {
        "v2_vocabulary": "collection-medium",
        "reason": "No instrument/collection-medium model in DHIS2 meta-model."
      },
      {
        "v2_vocabulary": "instrument-code",
        "reason": "No Instrument catalogue."
      },
      {
        "v2_vocabulary": "pregnancy-status",
        "reason": "Per-deployment."
      }
    ]
  },
  "govstack_payments": {
    "system": "govstack_payments",
    "concept_matches": [],
    "no_match": [
      {
        "v2_vocabulary": "enrollment-status",
        "reason": "The Payment BB does not model program enrollment. Enrollment is managed by the upstream Source BB (e.g., OpenSPP, openIMIS)."
      },
      {
        "v2_vocabulary": "eligibility-status",
        "reason": "The Payment BB does not model eligibility decisions. Eligibility is determined by the upstream Source BB before payment instructions are sent."
      },
      {
        "v2_vocabulary": "entitlement-status",
        "reason": "The Payment BB receives payment instructions but does not track entitlement lifecycle. Entitlement management belongs to the Source BB."
      },
      {
        "v2_vocabulary": "grievance-status",
        "reason": "The Payment BB does not include a grievance or complaints module."
      },
      {
        "v2_vocabulary": "grievance-type",
        "reason": "The Payment BB does not include a grievance or complaints module."
      },
      {
        "v2_vocabulary": "referral-status",
        "reason": "The Payment BB does not model inter-program referrals."
      },
      {
        "v2_vocabulary": "gender-type",
        "reason": "The Payment BB does not collect or store demographic data. Person identity is limited to a functional ID for payment routing."
      },
      {
        "v2_vocabulary": "sex",
        "reason": "The Payment BB does not collect or store demographic data."
      },
      {
        "v2_vocabulary": "marital-status",
        "reason": "The Payment BB does not collect or store demographic data."
      },
      {
        "v2_vocabulary": "education-level",
        "reason": "The Payment BB does not collect or store demographic data."
      },
      {
        "v2_vocabulary": "relationship-type",
        "reason": "The Payment BB does not model person-to-person or person-to-group relationships."
      },
      {
        "v2_vocabulary": "group-type",
        "reason": "The Payment BB does not model households, families, or groups. It operates at the individual beneficiary level for payment routing."
      },
      {
        "v2_vocabulary": "group-role",
        "reason": "The Payment BB does not model group membership or roles."
      },
      {
        "v2_vocabulary": "identifier-type",
        "reason": "The Payment BB uses a single opaque functional ID (payeeIdentity/payeeFunctionalID) for beneficiary identification. It does not categorize identifier types."
      },
      {
        "v2_vocabulary": "hazard-type",
        "reason": "The Payment BB does not model hazard or shock events."
      },
      {
        "v2_vocabulary": "event-severity",
        "reason": "The Payment BB does not model event severity or priority."
      },
      {
        "v2_vocabulary": "event-certainty",
        "reason": "The Payment BB does not model event certainty."
      },
      {
        "v2_vocabulary": "targeting-approach",
        "reason": "The Payment BB does not model targeting methodology. Targeting is done by the upstream Source BB."
      },
      {
        "v2_vocabulary": "conditionality-type",
        "reason": "The Payment BB does not model benefit conditionality."
      },
      {
        "v2_vocabulary": "voucher-format",
        "reason": "The Payment BB does not distinguish physical vs. electronic voucher format. Vouchers are created with a serial number and encrypted secret number; the delivery mechanism to the beneficiary is outside the BB scope."
      },
      {
        "v2_vocabulary": "benefit-frequency",
        "reason": "The Payment BB does not model payment frequency. It executes individual batch payment instructions on demand; scheduling and frequency are managed by the Source BB."
      }
    ]
  },
  "ocha_cod_ab": {
    "system": "ocha_cod_ab",
    "system_version": "COD-AB (current)",
    "source_repository": "https://data.humdata.org/dataset/cod-ab-global",
    "concept_matches": [
      {
        "v2_concept": "Location",
        "external_entity": "COD-AB feature (one row per admin unit)",
        "external_source": "Per-country COD-AB layer at https://data.humdata.org/dataset/cod-ab-<iso3>",
        "match": "close",
        "notes": "A COD-AB feature is an administrative boundary at a specific level. PublicSchema Location is broader (also covers non-administrative named places and bounded regions like flood zones and program coverage areas), so the relationship is: every COD-AB feature is a Location, but not every Location is a COD-AB feature. Each COD-AB layer holds one admin level; multi-level country coverage is split across files (adm0.shp, adm1.shp, ...). Hierarchy between levels is encoded redundantly in the lower-level rows (an adm2 row carries adm0_pcode, adm1_pcode, and adm2_pcode), and Location's `parent_location` reference reconstructs that hierarchy on the v2 side.\n"
      }
    ],
    "no_match": [
      {
        "reason": "COD-AB features are polygons, not points; no centroid is published. Derivable from geometry if needed.",
        "v2_property": "latitude"
      },
      {
        "reason": "Same as latitude.",
        "v2_property": "longitude"
      },
      {
        "reason": "COD-AB does not carry the localized name of the level itself (e.g., 'Region', 'District'); only the unit's own name.",
        "v2_property": "level_name"
      }
    ]
  },
  "opencrvs": {
    "system": "opencrvs",
    "system_version": "v2-event-service",
    "source_repository": "https://github.com/opencrvs/opencrvs-core",
    "source_branch": "develop",
    "country_config_reference": {
      "repository": "https://github.com/opencrvs/opencrvs-farajaland",
      "branch": "develop",
      "note": "Farajaland is OpenCRVS's reference country config. Entries flagged country_config: true have no fixed canonical type in v2 core; the Farajaland config is the canonical example of how a deployment defines birth, death, and marriage events.\n"
    },
    "concept_matches": [
      {
        "v2_concept": "VitalEvent",
        "external_entity": "EventDocument",
        "surface": "event_v2",
        "external_source": "packages/commons/src/events/EventDocument.ts#EventDocument",
        "match": "close",
        "notes": "EventDocument is the generic event envelope in v2: id, type (a free string such as \"BIRTH\" or \"DEATH\"), createdAt, updatedAt, actions, and trackingId. Our VitalEvent is the abstract supertype for civil registration events. The correspondence is close: both represent the occurrence entity, but EventDocument carries no domain fields; all content lives in the EventConfig.declaration fields of individual actions.\n",
        "decomposition": [
          {
            "opencrvs_field": "id",
            "target_concept": "VitalEvent",
            "target_property": null,
            "notes": "System UUID. No direct PublicSchema equivalent at the concept level; maps to an Identifier entry with identifier_type=tracking_id if persisted."
          },
          {
            "opencrvs_field": "type",
            "target_concept": "VitalEvent",
            "target_property": null,
            "notes": "Free string event type identifier (e.g. 'v2/BIRTH'). Country-configured; not a core enum."
          },
          {
            "opencrvs_field": "trackingId",
            "target_concept": "VitalEvent",
            "target_property": null,
            "notes": "Human-readable tracking ID (e.g. BKPX7CE). No PublicSchema property."
          },
          {
            "opencrvs_field": "actions",
            "target_concept": "CivilStatusRecord",
            "target_property": null,
            "notes": "Ordered list of ActionDocument entries. The most recent action with type=REGISTER carries registrationNumber, which maps to CivilStatusRecord.identifiers."
          },
          {
            "opencrvs_field": "createdAt",
            "target_concept": "VitalEvent",
            "target_property": null,
            "notes": "Timestamp of event creation in the system, not the occurrence date. PublicSchema event_date comes from country-configured declaration fields."
          }
        ]
      },
      {
        "v2_concept": "Birth",
        "external_entity": "EventDocument (type='BIRTH', country-configured)",
        "surface": "country_config",
        "external_source": "src/events/birth/index.ts#birthEvent",
        "country_config": true,
        "match": "broad",
        "confidence": "low",
        "notes": "In v2 core there is no BirthRegistration type. A birth event is an EventDocument whose type string is set to the country's birth event id (e.g. the Farajaland constant Event.Birth). All birth-specific fields (child name, birthDate, parentage, birthType, attendant, weight) live in the EventConfig.declaration form defined by the country config. Match is broad because the EventDocument envelope is genuinely wider than our Birth concept.\n"
      },
      {
        "v2_concept": "Death",
        "external_entity": "EventDocument (type='DEATH', country-configured)",
        "surface": "country_config",
        "external_source": "src/events/death/index.ts#deathEvent",
        "country_config": true,
        "match": "broad",
        "confidence": "low",
        "notes": "Same pattern as Birth. A death event is an EventDocument whose type string is set to the country's death event id. Death-specific fields (deceased name, cause of death, manner of death, medical certifier) are country-configured EventConfig.declaration fields; none are typed at the v2 core level.\n"
      },
      {
        "v2_concept": "Marriage",
        "external_entity": "EventDocument (type='marriage', country-configured)",
        "surface": "country_config",
        "external_source": "src/events/utils/types.ts#Event",
        "country_config": true,
        "match": "broad",
        "notes": "The Farajaland Event enum defines Event.Marriage = 'marriage', confirming the convention. A full EventConfig for marriage is not present in the Farajaland reference clone; the same EventDocument + country EventConfig pattern applies. Marriage-specific fields (bride/groom or party_1/party_2, witnesses, typeOfMarriage) would be country-configured EventConfig.declaration fields. Match is broad and confidence is null pending a concrete EventConfig example.\n"
      },
      {
        "v2_concept": "CivilStatusRecord",
        "external_entity": "RegisterAction",
        "surface": "event_v2",
        "external_source": "packages/commons/src/events/ActionDocument.ts#RegisterAction",
        "match": "related",
        "notes": "RegisterAction is an ActionDocument variant (type=REGISTER) that carries a registrationNumber field. This is the closest v2 core equivalent to our CivilStatusRecord: the act of registration produces a registration number, which is the legal acte identifier. However, RegisterAction is an action within an EventDocument, not a standalone record; the structural roles differ. The registrationNumber field is optional (nullable) and is always present on accepted registrations.\n",
        "decomposition": [
          {
            "opencrvs_field": "registrationNumber",
            "target_concept": "CivilStatusRecord",
            "target_property": "identifiers",
            "notes": "Maps to an Identifier entry with identifier_type following the event type (birth_registration_number, death_registration_number, etc.)."
          },
          {
            "opencrvs_field": "declaration",
            "target_concept": "CivilStatusRecord",
            "target_property": null,
            "notes": "ActionUpdate record of field-level changes at registration time; country-configured, not typed at core level."
          },
          {
            "opencrvs_field": "createdAt",
            "target_concept": "CivilStatusRecord",
            "target_property": null,
            "notes": "Timestamp of the register action. Approximates the record creation date."
          },
          {
            "opencrvs_field": "createdBy",
            "target_concept": "CivilStatusRecord",
            "target_property": null,
            "notes": "Registrar identity; no direct PublicSchema property."
          }
        ]
      },
      {
        "v2_concept": "Certificate",
        "external_entity": "PrintCertificateAction",
        "surface": "event_v2",
        "external_source": "packages/commons/src/events/ActionDocument.ts#PrintCertificateAction",
        "match": "related",
        "notes": "PrintCertificateAction is an ActionDocument variant (type=PRINT_CERTIFICATE). It carries an optional templateId content field. This is structurally narrower than our Certificate concept, which models the issued document with issuance metadata (issue date, issuing office, format, certificate number). PrintCertificateAction records the act of printing; it does not fully represent the certificate as a legal document object. Match is related rather than close because the scope has narrowed from v1's Certificate type.\n",
        "decomposition": [
          {
            "opencrvs_field": "content.templateId",
            "target_concept": "Certificate",
            "target_property": "certificate_document_type",
            "notes": "Country-configured template identifier. Mapping to document type requires knowledge of the local template catalogue."
          },
          {
            "opencrvs_field": "createdAt",
            "target_concept": "Certificate",
            "target_property": null,
            "notes": "Print timestamp. Approximates issue date."
          },
          {
            "opencrvs_field": "createdBy",
            "target_concept": "Certificate",
            "target_property": null,
            "notes": "Who printed the certificate; no direct PublicSchema property."
          },
          {
            "opencrvs_field": "createdAtLocation",
            "target_concept": "Certificate",
            "target_property": null,
            "notes": "Location of the registrar who printed; approximates issuing office."
          }
        ]
      },
      {
        "v2_concept": "PaternityRecognition",
        "external_entity": "RequestedCorrectionAction / ApprovedCorrectionAction",
        "surface": "event_v2",
        "external_source": "packages/commons/src/events/ActionDocument.ts#RequestedCorrectionAction",
        "match": "related",
        "notes": "PaternityRecognition remains without a first-class event type in v2. The correction workflow (ActionType.REQUEST_CORRECTION followed by ActionType.APPROVE_CORRECTION) is the operational mechanism for amending a birth record to add or change parentage information. The match is related for the same reason as v1: the target is a workflow action pair, not an event type. A country config could define a dedicated \"paternity recognition\" event type using a separate EventConfig.\n"
      }
    ],
    "no_match": [
      {
        "v2_concept": "FetalDeath",
        "reason": "Not modelled as a distinct event type in v2 core. A country config could define a fetal death event; the Farajaland reference config does not. No fixed v2 core equivalent.\n"
      },
      {
        "v2_concept": "MarriageTermination",
        "reason": "Not modelled in v2 core or the Farajaland reference config. Neither divorce nor annulment registration exists as a first-class event type.\n"
      },
      {
        "v2_concept": "Adoption",
        "reason": "Not modelled in v2 core or the Farajaland reference config. Adoption scenarios would require a country-specific EventConfig.\n"
      },
      {
        "v2_concept": "Legitimation",
        "reason": "Not modelled in v2 core. Same pattern as PaternityRecognition: operationally a correction action on an existing birth record.\n"
      },
      {
        "v2_concept": "CivilStatusAnnotation",
        "reason": "No reified marginal-annotation type in v2. ActionBase carries an annotation field (an untyped key-value record) for action-specific metadata, but this is not an annotation in the legal CRVS sense (a signed marginal note on a register entry).\n"
      },
      {
        "v2_concept": "FamilyRegister",
        "reason": "V2 is event-record centric. There is no concept of a family register (livret de famille, koseki, hukou); families are not modelled as a tracked unit in v2 core or the Farajaland reference config.\n"
      },
      {
        "v2_concept": "Person",
        "reason": "V2 core has no Person type. All person data (name, date of birth, demographic attributes) lives in country-configured declaration fields inside EventDocument.actions[].declaration, a Record<string, FieldValue> keyed by country-specific strings. There is no reified temporal-snapshot Person entity in the event service.\n"
      },
      {
        "v2_concept": "Parent",
        "reason": "Our Parent is a reified link entity (Person + parental_role). V2 core has no such type. In Farajaland, parent data appears as declaration field groups with keys like mother.firstname, father.surname; the role is encoded in the field-key prefix, not a typed enum.\n"
      },
      {
        "v2_vocabulary": "enrollment-status",
        "reason": "OpenCRVS has no concept of program enrollment. Civil registration records vital events; it does not track program participation.\n"
      },
      {
        "v2_vocabulary": "eligibility-status",
        "reason": "No eligibility assessment in OpenCRVS. Eligibility determination is a social protection function with no CRVS equivalent.\n"
      },
      {
        "v2_vocabulary": "benefit-frequency",
        "reason": "No benefit disbursement cycle in OpenCRVS. Payments in OpenCRVS are one-time service fees, not recurring benefit transfers.\n"
      },
      {
        "v2_vocabulary": "benefit-modality",
        "reason": "No benefit type or modality concept in OpenCRVS. Cash, in-kind, and voucher transfers are social protection constructs absent from CRVS.\n"
      },
      {
        "v2_vocabulary": "event-certainty",
        "reason": "No probability or certainty scoring in OpenCRVS. Used in v2 for targeting and assessment confidence levels with no CRVS analog.\n"
      },
      {
        "v2_vocabulary": "conditionality-type",
        "reason": "Conditionalities (co-responsibilities attached to benefits) are a social protection concept with no equivalent in civil registration.\n"
      },
      {
        "v2_vocabulary": "delivery-channel",
        "reason": "Delivery channel (how benefits reach beneficiaries) is a disbursement concept absent from OpenCRVS.\n"
      },
      {
        "v2_vocabulary": "grievance-status",
        "reason": "OpenCRVS has no formal grievance management module. Complaints and appeals are social protection constructs.\n"
      },
      {
        "v2_vocabulary": "grievance-type",
        "reason": "Same as grievance-status: no grievance classification in OpenCRVS."
      },
      {
        "v2_vocabulary": "group-role",
        "reason": "V2 group-role covers household membership roles in a social protection context. OpenCRVS captures family relationships as field-key prefixes in declaration data, not a shared enumeration.\n"
      },
      {
        "v2_vocabulary": "group-type",
        "reason": "V2 group-type distinguishes household, family, farm, and other group structures used in social protection targeting. OpenCRVS has no equivalent grouping concept.\n"
      },
      {
        "v2_vocabulary": "hazard-type",
        "reason": "Hazard classification is used in social protection for shock-responsive programming. No analog in civil registration.\n"
      },
      {
        "v2_vocabulary": "referral-status",
        "reason": "Referral tracking between programs is a social protection construct with no civil registration equivalent.\n"
      },
      {
        "v2_vocabulary": "event-severity",
        "reason": "Severity scoring (for shocks, grievances, or needs) is a social protection assessment concept absent from OpenCRVS.\n"
      },
      {
        "v2_vocabulary": "targeting-approach",
        "reason": "Program targeting methodology is a social protection planning concept with no civil registration equivalent.\n"
      },
      {
        "v2_vocabulary": "literacy",
        "reason": "OpenCRVS v2 (and the Farajaland reference config) does not include a literacy field. The UNSD binary literacy classification has no counterpart in v2 core or country configuration patterns.\n"
      },
      {
        "v2_vocabulary": "employment-status",
        "reason": "OpenCRVS v2 does not include an employment status field. The ILO tripartite classification has no counterpart in v2 core.\n"
      },
      {
        "v2_vocabulary": "status-in-employment",
        "reason": "OpenCRVS v2 does not include a status-in-employment field. The ILO ICSE-18 categories have no counterpart in v2 core.\n"
      },
      {
        "v2_vocabulary": "crvs/registration-type",
        "reason": "Semantic mismatch. Our registration-type describes the timing and procedural route of registration (current, late, court_ordered, reconstruction). V2 EventDocument.type describes which event category is being registered (birth, death, marriage); that dimension maps to our civil-status-record-type vocabulary, not registration-type.\n"
      }
    ]
  },
  "openimis": {
    "system": "openimis",
    "system_version": "develop",
    "source_repository": "https://github.com/openimis/openimis-be_py",
    "source_branch": "develop",
    "fhir_repository": "https://github.com/openimis/openimis-be-api_fhir_r4_py",
    "fhir_branch": "develop",
    "concept_matches": [],
    "no_match": [
      {
        "v2_vocabulary": "benefit-frequency",
        "reason": "OpenIMIS does not define a payment frequency vocabulary. Payment cycle cadence is configured per product as numeric date fields (start/end dates and recurring periods), not as a categorical enumeration."
      },
      {
        "v2_vocabulary": "benefit-modality",
        "reason": "OpenIMIS does not have an explicit benefit modality vocabulary. The social protection module handles cash transfers; in-kind or voucher modalities are not represented as a categorical field."
      },
      {
        "v2_vocabulary": "conditionality-type",
        "reason": "OpenIMIS does not model conditionality as a categorical attribute on benefit plans. Conditions are managed outside the core schema."
      },
      {
        "v2_vocabulary": "eligibility-status",
        "reason": "OpenIMIS does not have a dedicated eligibility determination status vocabulary. Eligibility logic is embedded in benefit plan rules and BeneficiaryStatus; there is no separate EligibilityDecision record with its own status field."
      },
      {
        "v2_vocabulary": "hazard-type",
        "reason": "OpenIMIS does not model hazard or shock events. The system has no shock-registry or emergency-trigger module."
      },
      {
        "v2_vocabulary": "marital-status",
        "reason": "OpenIMIS does not include a marital status vocabulary in the extracted modules. The insuree model does not have a marital status field in the social protection or insuree modules covered here."
      },
      {
        "v2_vocabulary": "referral-status",
        "reason": "OpenIMIS does not have a referral module or referral status vocabulary in the extracted codebase. The grievance module handles complaints, not inter-program referrals."
      },
      {
        "v2_vocabulary": "targeting-approach",
        "reason": "OpenIMIS does not expose a targeting approach vocabulary. The benefit plan configuration does not categorise the method used to identify beneficiaries as a controlled value set."
      },
      {
        "v2_vocabulary": "event-severity",
        "reason": "v2 event-severity classifies hazard/disaster impact (OASIS CAP v1.2). OpenIMIS's closest scale is grievance TicketPriority (Critical/High/Normal/Low) on the grievance_social_protection module, which measures grievance urgency, not disaster impact. The domains differ, so no semantic mapping is offered. If OpenIMIS deployments record hazard events, they would need a separate severity field aligned with CAP."
      },
      {
        "v2_vocabulary": "event-certainty",
        "reason": "OpenIMIS does not model event certainty. This vocabulary is used for shock or hazard events, which are outside the scope of the openIMIS modules."
      }
    ]
  },
  "openspp": {
    "system": "openspp",
    "system_version": "19.0",
    "source_repository": "https://github.com/OpenSPP/OpenSPP2",
    "source_branch": "19.0",
    "concept_matches": [],
    "no_match": [
      {
        "v2_vocabulary": "benefit-frequency",
        "reason": "OpenSPP does not have a vocabulary or selection enum for benefit delivery frequency. Cycle recurrence in OpenSPP is configured via date ranges and the Odoo recurrence infrastructure (RRULE), not a controlled vocabulary."
      },
      {
        "v2_vocabulary": "event-certainty",
        "reason": "No OpenSPP vocabulary or selection for data certainty or confidence level on recorded attributes."
      },
      {
        "v2_vocabulary": "conditionality-type",
        "reason": "OpenSPP does not expose a conditionality classification vocabulary. Whether a program is conditional or unconditional is implicit in program configuration, not a controlled vocabulary field."
      },
      {
        "v2_vocabulary": "delivery-channel",
        "reason": "OpenSPP does not have a delivery channel vocabulary. Payment delivery mechanism is determined by the FSP (Financial Service Provider) configuration, not a separate enumeration."
      },
      {
        "v2_vocabulary": "grievance-type",
        "reason": "OpenSPP GRM does not have a structured grievance category vocabulary in the extracted data. Ticket categorization is done through configurable category records (spp.grm.ticket.category), not a fixed selection enum, making a code-level mapping impossible without deployment-specific data."
      },
      {
        "v2_vocabulary": "hazard-type",
        "reason": "OpenSPP spp_hazard module defines hazard incidents but does not expose a hazard type classification vocabulary or selection in the extracted data. Hazard types would be configured per deployment."
      },
      {
        "v2_vocabulary": "referral-status",
        "reason": "OpenSPP does not have a referral module or referral lifecycle vocabulary in the extracted data. The spp_case_base module tracks intake source (including 'referral') but not outbound referral status."
      },
      {
        "v2_vocabulary": "targeting-approach",
        "reason": "OpenSPP does not have a controlled vocabulary for targeting methodology. Targeting is implemented through configurable filter rules and scoring models (spp_scoring), not a classification vocabulary."
      },
      {
        "v2_vocabulary": "script",
        "reason": "No OpenSPP vocabulary for writing scripts (ISO 15924). OpenSPP language vocabulary uses ISO 639 codes only."
      },
      {
        "v2_vocabulary": "region",
        "reason": "No OpenSPP vocabulary for UN M49 geographic regions. Country selection uses ISO 3166-1; regional groupings are not exposed as a controlled vocabulary."
      }
    ]
  }
}
